<?xml version="1.0" encoding="utf-8"?>
<DemandSet id="0" project_id="0">
   <demandProfile id="1" link_id_org="-147">
      <demand vehicle_type_id="0">1,2,3,4,5</demand>
   </demandProfile>
   <demandProfile id="2" link_id_org="-150">
      <demand vehicle_type_id="0">1,2,3,4,5</demand>
   </demandProfile>
   <demandProfile id="3" link_id_org="-161">
      <demand vehicle_type_id="0">1,2,3,4,5</demand>
   </demandProfile>
   <demandProfile id="4" link_id_org="-172">
      <demand vehicle_type_id="0">1,2,3,4,5</demand>
   </demandProfile>
   <demandProfile id="5" link_id_org="-184">
      <demand vehicle_type_id="0">1,2,3,4,5</demand>
   </demandProfile>
   <demandProfile id="6" link_id_org="-194">
      <demand vehicle_type_id="0">1,2,3,4,5</demand>
   </demandProfile>
   <demandProfile id="7" link_id_org="-202">
      <demand vehicle_type_id="0">1,2,3,4,5</demand>
   </demandProfile>
   <demandProfile id="8" link_id_org="-203">
      <demand vehicle_type_id="0">1,2,3,4,5</demand>
   </demandProfile>
   <demandProfile id="9" link_id_org="-204">
      <demand vehicle_type_id="0">1,2,3,4,5</demand>
   </demandProfile>
   <demandProfile id="10" link_id_org="-205">
      <demand vehicle_type_id="0">1,2,3,4,5</demand>
   </demandProfile>
   <demandProfile id="11" link_id_org="-212">
      <demand vehicle_type_id="0">1,2,3,4,5</demand>
   </demandProfile>
   <demandProfile id="12" link_id_org="-216">
      <demand vehicle_type_id="0">1,2,3,4,5</demand>
   </demandProfile>
   <demandProfile id="13" link_id_org="-217">
      <demand vehicle_type_id="0">1,2,3,4,5</demand>
   </demandProfile>
   <demandProfile id="14" link_id_org="-83">
      <demand vehicle_type_id="0">1,2,3,4,5</demand>
   </demandProfile>
   <demandProfile id="15" link_id_org="-232">
      <demand vehicle_type_id="0">1,2,3,4,5</demand>
   </demandProfile>
   <demandProfile id="16" link_id_org="-242">
      <demand vehicle_type_id="0">1,2,3,4,5</demand>
   </demandProfile>
   <demandProfile id="17" link_id_org="-248">
      <demand vehicle_type_id="0">1,2,3,4,5</demand>
   </demandProfile>
   <demandProfile id="18" link_id_org="-268">
      <demand vehicle_type_id="0">1,2,3,4,5</demand>
   </demandProfile>
   <demandProfile id="19" link_id_org="-193">
      <demand vehicle_type_id="0">1,2,3,4,5</demand>
   </demandProfile>
   <demandProfile id="20" link_id_org="-265">
      <demand vehicle_type_id="0">1,2,3,4,5</demand>
   </demandProfile>
   <demandProfile id="21" link_id_org="-109">
      <demand vehicle_type_id="0">1,2,3,4,5</demand>
   </demandProfile>
   <demandProfile id="22" link_id_org="-215">
      <demand vehicle_type_id="0">1,2,3,4,5</demand>
   </demandProfile>
   <demandProfile id="23" link_id_org="-249">
      <demand vehicle_type_id="0">1,2,3,4,5</demand>
   </demandProfile>
   <demandProfile id="24" link_id_org="-277">
      <demand vehicle_type_id="0">1,2,3,4,5</demand>
   </demandProfile>
</DemandSet>